{
  "recentFiles": [
    {
      "basename": "README",
      "path": "README.md"
    },
    {
      "basename": "编程心得",
      "path": "READING/编程心得.md"
    },
    {
      "basename": "The cheatsheet of gdb",
      "path": "LinuxTool/gcc&gdb/The cheatsheet of gdb.md"
    },
    {
      "basename": "M1 打印进程树 (pstree)",
      "path": "NJUOS/M1 打印进程树 (pstree).md"
    },
    {
      "basename": "数据表示知识点清单",
      "path": "NJUICS/theory/02 数据的机器级表示与运算/数据表示知识点清单.md"
    },
    {
      "basename": "The cheatsheet of Data Representation",
      "path": "NJUICS/theory/02 数据的机器级表示与运算/The cheatsheet of Data Representation.md"
    },
    {
      "basename": "The note of Makefile",
      "path": "LinuxTool/gcc&gdb/The note of Makefile.md"
    },
    {
      "basename": "数据表示常见问题解答",
      "path": "NJUICS/theory/02 数据的机器级表示与运算/数据表示常见问题解答.md"
    },
    {
      "basename": "05-数据的机器级表示",
      "path": "NJUICS/lecture/L5 数据的机器级表示/05-数据的机器级表示.md"
    },
    {
      "basename": "03-NEMU 框架选讲 (1) 编译运行",
      "path": "NJUICS/lecture/L3-4 NEMU 框架选讲/03-NEMU 框架选讲 (1) 编译运行.md"
    },
    {
      "basename": "04-NEMU 框架选讲 (2) 代码导读",
      "path": "NJUICS/lecture/L3-4 NEMU 框架选讲/04-NEMU 框架选讲 (2) 代码导读.md"
    },
    {
      "basename": "What every computer scientist should know about floating-point arithmetic",
      "path": "NJUICS/lecture/L5 数据的机器级表示/What every computer scientist should know about floating-point arithmetic.pdf"
    },
    {
      "basename": "计算bit串中1的个数",
      "path": "NJUICS/lecture/L5 数据的机器级表示/计算bit串中1的个数.pdf"
    },
    {
      "basename": "start",
      "path": "CMU-CSAPP/3 attacklab/start.md"
    },
    {
      "basename": "csapp2p.excalidraw",
      "path": "CMU-CSAPP/2 bomblab/csapp2p.excalidraw.md"
    },
    {
      "basename": "phase_5.excalidraw",
      "path": "CMU-CSAPP/2 bomblab/phase_5.excalidraw.md"
    },
    {
      "basename": "phase_2.excalidraw",
      "path": "CMU-CSAPP/2 bomblab/phase_2.excalidraw.md"
    },
    {
      "basename": "phase_3.excalidraw",
      "path": "CMU-CSAPP/2 bomblab/phase_3.excalidraw.md"
    },
    {
      "basename": "phase_4.excalidraw",
      "path": "CMU-CSAPP/2 bomblab/phase_4.excalidraw.md"
    },
    {
      "basename": "phase_1.excalidraw",
      "path": "CMU-CSAPP/2 bomblab/phase_1.excalidraw.md"
    },
    {
      "basename": "datalab-note",
      "path": "CMU-CSAPP/1 datalab/datalab-note.md"
    },
    {
      "basename": "README",
      "path": "CS61B/README.md"
    },
    {
      "basename": "datalab",
      "path": "CMU-CSAPP/1 datalab/datalab.pdf"
    },
    {
      "basename": "ui.c",
      "path": "NJUICS/code/monitor/ui.c.md"
    },
    {
      "basename": "一些辅助函数",
      "path": "NJUICS/code/一些辅助函数.md"
    },
    {
      "basename": "NEMU-Makefile",
      "path": "NJUICS/code/NEMU-Makefile.md"
    },
    {
      "basename": "parse_args()",
      "path": "NJUICS/code/parse_args().md"
    },
    {
      "basename": "vscode configuration",
      "path": "NJUICS/code/vscode configuration.md"
    },
    {
      "basename": "i386 2.3 Registers",
      "path": "NJUICS/manual/i386 2.3 Registers.md"
    },
    {
      "basename": "Monitor",
      "path": "NJUICS/note/PA1/Monitor.md"
    },
    {
      "basename": "Drawing 2022-11-28 16.50.15.excalidraw",
      "path": "NJUICS/note/PA1/Drawing 2022-11-28 16.50.15.excalidraw.md"
    },
    {
      "basename": "IEEE754 Float",
      "path": "attachments/IEEE754 Float.png"
    },
    {
      "basename": "log.py",
      "path": "NJUICS/lecture/L5 数据的机器级表示/log.py.md"
    },
    {
      "basename": "02-C 语言拾遗 (2) 编程实践",
      "path": "NJUICS/lecture/L1-2 C语言拾遗/02-C 语言拾遗 (2) 编程实践.md"
    },
    {
      "basename": "01-C 语言拾遗 (1) 机制",
      "path": "NJUICS/lecture/L1-2 C语言拾遗/01-C 语言拾遗 (1) 机制.md"
    },
    {
      "basename": "L2 Description",
      "path": "NJUICS/lab/Lab2 x86-64 内联汇编/L2 Description.md"
    },
    {
      "basename": "L1 Description",
      "path": "NJUICS/lab/Lab1 大整数运算/L1 Description.md"
    },
    {
      "basename": "Notes-Lab1 大整数运算",
      "path": "NJUICS/lab/Lab1 大整数运算/Notes-Lab1 大整数运算.md"
    },
    {
      "basename": "从泰勒公式到欧拉公式",
      "path": "math/从泰勒公式到欧拉公式.md"
    },
    {
      "basename": "IntroToPython",
      "path": "CS61A/canvasNote/IntroToPython.canvas"
    },
    {
      "basename": "2023-01-16",
      "path": "diary/2023-01-16.md"
    },
    {
      "basename": "未命名",
      "path": "NJUICS/lecture/未命名.md"
    },
    {
      "basename": "Vim map",
      "path": "LinuxTool/vim/Vim map.md"
    },
    {
      "basename": "Ascii Draw In Vim",
      "path": "LinuxTool/vim/Ascii Draw In Vim.md"
    },
    {
      "basename": "1 The note of Vim",
      "path": "LinuxTool/vim/1 The note of Vim.md"
    },
    {
      "basename": "6 版本控制(Git)",
      "path": "The Missing Semester/6 版本控制(Git).md"
    }
  ],
  "omittedPaths": [],
  "maxLength": null,
  "openType": "tab"
}