{
  "accentColor": "",
  "theme": "moonstone",
  "baseFontSize": 18,
  "cssTheme": "Prism",
  "translucency": false,
  "monospaceFontFamily": "FiraCode Nerd Font,苹方-简",
  "nativeMenus": false,
  "baseFontSizeAction": false,
  "showViewHeader": true,
  "enabledCssSnippets": [
    "coffebean-按文件类型显示对应图标",
    "custom_callouts",
    "img",
    "multi_col",
    "code1",
    "callout_aside",
    "supercharged-links-gen",
    "image",
    "callout1",
    "basic",
    "code"
  ],
  "textFontFamily": "Bookerly,LXGW WenKai,LXGW WenKai GB Screen,苹方-简",
  "interfaceFontFamily": "Bookerly,苹方-简"
}