{
  "main": {
    "id": "9578adbec0afc5b2",
    "type": "split",
    "children": [
      {
        "id": "079c3eb20fe1e874",
        "type": "tabs",
        "children": [
          {
            "id": "61c5bdc9975a6a03",
            "type": "leaf",
            "state": {
              "type": "markdown",
              "state": {
                "file": "pa2020/tutorial/PA1 开天辟地的篇章 最简单的计算机/1-3 RTFSC 2020.md",
                "mode": "preview",
                "backlinks": true,
                "source": true
              }
            }
          }
        ]
      }
    ],
    "direction": "vertical"
  },
  "left": {
    "id": "44c334809e1b0082",
    "type": "split",
    "children": [
      {
        "id": "890e19d61646196f",
        "type": "tabs",
        "children": [
          {
            "id": "bf178dff9f426baa",
            "type": "leaf",
            "state": {
              "type": "file-explorer",
              "state": {
                "sortOrder": "alphabetical"
              }
            }
          },
          {
            "id": "f8b50e12f701171c",
            "type": "leaf",
            "state": {
              "type": "search",
              "state": {
                "query": "",
                "matchingCase": false,
                "explainSearch": false,
                "collapseAll": false,
                "extraContext": false,
                "sortOrder": "alphabetical"
              }
            }
          },
          {
            "id": "539eef4d04534f97",
            "type": "leaf",
            "state": {
              "type": "starred",
              "state": {}
            }
          }
        ]
      }
    ],
    "direction": "horizontal",
    "width": 289.5
  },
  "right": {
    "id": "3a153ac8983db304",
    "type": "split",
    "children": [
      {
        "id": "c87440566f5123e1",
        "type": "tabs",
        "dimension": 27.08333333333333,
        "children": [
          {
            "id": "ef3b7f2c6df00cf0",
            "type": "leaf",
            "state": {
              "type": "backlink",
              "state": {
                "file": "pa2020/tutorial/PA1 开天辟地的篇章 最简单的计算机/1-3 RTFSC 2020.md",
                "collapseAll": false,
                "extraContext": false,
                "sortOrder": "alphabetical",
                "showSearch": false,
                "searchQuery": "",
                "backlinkCollapsed": false,
                "unlinkedCollapsed": true
              }
            }
          },
          {
            "id": "aa933b58d0a6c5ae",
            "type": "leaf",
            "state": {
              "type": "tag",
              "state": {
                "sortOrder": "frequency",
                "useHierarchy": true
              }
            }
          },
          {
            "id": "001d31554c7f2bac",
            "type": "leaf",
            "state": {
              "type": "advanced-tables-toolbar",
              "state": {}
            }
          },
          {
            "id": "0c1a9dde429a1099",
            "type": "leaf",
            "state": {
              "type": "calendar",
              "state": {}
            }
          },
          {
            "id": "1836f056068a04f7",
            "type": "leaf",
            "state": {
              "type": "reminder-list",
              "state": {}
            }
          }
        ],
        "currentTab": 3
      },
      {
        "id": "ec1ce9afb0ad6835",
        "type": "tabs",
        "dimension": 20.170454545454543,
        "children": [
          {
            "id": "5cbfcd350af9b62e",
            "type": "leaf",
            "state": {
              "type": "outgoing-link",
              "state": {
                "file": "pa2020/tutorial/PA1 开天辟地的篇章 最简单的计算机/1-3 RTFSC 2020.md",
                "linksCollapsed": false,
                "unlinkedCollapsed": true
              }
            }
          }
        ]
      },
      {
        "id": "c8bf216c9c77d4e7",
        "type": "tabs",
        "dimension": 52.74621212121212,
        "children": [
          {
            "id": "1a8a2d36901663aa",
            "type": "leaf",
            "state": {
              "type": "outline",
              "state": {
                "file": "pa2020/tutorial/PA1 开天辟地的篇章 最简单的计算机/1-3 RTFSC 2020.md"
              }
            }
          }
        ]
      }
    ],
    "direction": "horizontal",
    "width": 314.5
  },
  "left-ribbon": {
    "hiddenItems": {
      "obsidian-excalidraw-plugin:New Excalidraw drawing": false,
      "switcher:Open quick switcher": false,
      "graph:Open graph view": false,
      "daily-notes:Open today's daily note": false,
      "templates:Insert template": false,
      "command-palette:Open command palette": false,
      "workspaces:Manage workspace layouts": false,
      "canvas:Create new canvas": false,
      "obsidian-memos:Memos": false
    }
  },
  "active": "61c5bdc9975a6a03",
  "lastOpenFiles": [
    "pa2020/tutorial/PA1 开天辟地的篇章 最简单的计算机/1-1 在开始愉快的PA之旅之前.md",
    "pa2020/tutorial/PA1 开天辟地的篇章 最简单的计算机/1-2 开天辟地的篇章.md",
    "pa2020/tutorial/PA0 世界诞生的前夜 开发环境配置/0 intro.md",
    "pa2020/tutorial/PA1 开天辟地的篇章 最简单的计算机/1 Intro.md",
    "LinuxTool/gcc&gdb/The note of Makefile.md",
    "LinuxTool/dotfiles/1 chezmoi 优雅的文档设计.md",
    "diary/2022-12-18.md",
    "LinuxTool/tmux/Tmux-Getting-Started.md",
    "LinuxTool/tmux/Tmux.excalidraw.md",
    "LinuxTool/tmux/1 The art of Tmux.md"
  ]
}